topsis_vandana_102303443/__init__.py
topsis_vandana_102303443/topsis.py
topsis_vandana_102303443-1.0.0.dist-info/METADATA
topsis_vandana_102303443-1.0.0.dist-info/WHEEL
topsis_vandana_102303443-1.0.0.dist-info/entry_points.txt
topsis_vandana_102303443-1.0.0.dist-info/top_level.txt
topsis_vandana_102303443-1.0.0.dist-info/RECORD
