Metadata-Version: 2.4
Name: Topsis-Vandana-102303443
Version: 1.0.0
Summary: Python package for TOPSIS method
Author: Vandana
Author-email: vandanaverma2506@gmail.com
Requires-Python: >=3.7
Requires-Dist: pandas
Requires-Dist: numpy
Dynamic: author
Dynamic: author-email
Dynamic: description
Dynamic: description-content-type
Dynamic: requires-dist
Dynamic: requires-python
Dynamic: summary
